odoo8_addon_l10n_it_invoices_data_communication-8.0.1.1.0-nspkg.pth
odoo_addons/l10n_it_invoices_data_communication/README.rst
odoo_addons/l10n_it_invoices_data_communication/__init__.py
odoo_addons/l10n_it_invoices_data_communication/__openerp__.py
odoo_addons/l10n_it_invoices_data_communication/i18n/it.po
odoo_addons/l10n_it_invoices_data_communication/i18n/l10n_it_invoices_data_communication.pot
odoo_addons/l10n_it_invoices_data_communication/models/__init__.py
odoo_addons/l10n_it_invoices_data_communication/models/account.py
odoo_addons/l10n_it_invoices_data_communication/models/account_invoice.py
odoo_addons/l10n_it_invoices_data_communication/models/communication.py
odoo_addons/l10n_it_invoices_data_communication/readme/CONTRIBUTORS.rst
odoo_addons/l10n_it_invoices_data_communication/readme/CREDITS.rst
odoo_addons/l10n_it_invoices_data_communication/readme/DESCRIPTION.rst
odoo_addons/l10n_it_invoices_data_communication/readme/ROADMAP.rst
odoo_addons/l10n_it_invoices_data_communication/security/ir.model.access.csv
odoo_addons/l10n_it_invoices_data_communication/security/security.xml
odoo_addons/l10n_it_invoices_data_communication/static/description/icon.png
odoo_addons/l10n_it_invoices_data_communication/static/description/index.html
odoo_addons/l10n_it_invoices_data_communication/views/account.xml
odoo_addons/l10n_it_invoices_data_communication/views/account_invoice_view.xml
odoo_addons/l10n_it_invoices_data_communication/views/comunicazione.xml
odoo_addons/l10n_it_invoices_data_communication/wizard/__init__.py
odoo_addons/l10n_it_invoices_data_communication/wizard/compute_fiscal_document_type.py
odoo_addons/l10n_it_invoices_data_communication/wizard/compute_fiscal_document_type_view.xml
odoo_addons/l10n_it_invoices_data_communication/wizard/export_file.py
odoo_addons/l10n_it_invoices_data_communication/wizard/export_file_view.xml
odoo_addons/l10n_it_invoices_data_communication/wizard/split_big_communication.py
odoo8_addon_l10n_it_invoices_data_communication-8.0.1.1.0.dist-info/METADATA
odoo8_addon_l10n_it_invoices_data_communication-8.0.1.1.0.dist-info/WHEEL
odoo8_addon_l10n_it_invoices_data_communication-8.0.1.1.0.dist-info/namespace_packages.txt
odoo8_addon_l10n_it_invoices_data_communication-8.0.1.1.0.dist-info/top_level.txt
odoo8_addon_l10n_it_invoices_data_communication-8.0.1.1.0.dist-info/RECORD
