Metadata-Version: 2.1
Name: odoo8-addon-l10n-it-invoices-data-communication
Version: 8.0.1.1.0
Summary: Comunicazione dati fatture (c.d. "nuovo spesometro" o "esterometro")
Home-page: https://github.com/OCA/l10n-italy/tree/8.0/l10n_it_invoices_data_communication
Author: Openforce di Camilli Alessandro, Odoo Community Association (OCA)
Author-email: support@odoo-community.org
License: LGPL-3
Platform: UNKNOWN
Classifier: Programming Language :: Python
Classifier: Framework :: Odoo
Classifier: License :: OSI Approved :: GNU Lesser General Public License v3 (LGPLv3)
Requires-Python: ~=2.7
Requires-Dist: odoo8-addon-account-invoice-entry-date
Requires-Dist: odoo8-addon-l10n-it-account
Requires-Dist: odoo8-addon-l10n-it-account-tax-kind
Requires-Dist: odoo8-addon-l10n-it-codici-carica
Requires-Dist: odoo8-addon-l10n-it-esigibilita-iva
Requires-Dist: odoo8-addon-l10n-it-fiscal-document-type
Requires-Dist: odoo8-addon-l10n-it-fiscalcode
Requires-Dist: odoo (<9.0a,>=8.0a)
